metis_lib/__init__.py
metis_lib/args.py
metis_lib/result.py
metis_lib/utils.py
test/__init__.py
test/args.py
metis_lib-0.1.3.dist-info/METADATA
metis_lib-0.1.3.dist-info/WHEEL
metis_lib-0.1.3.dist-info/top_level.txt
metis_lib-0.1.3.dist-info/RECORD
