Metadata-Version: 2.1
Name: metis-lib
Version: 0.1.3
Summary: metis library
Home-page: UNKNOWN
Author: phddys
Author-email: phddys@gmail.com
License: UNKNOWN
Keywords: metis_lib
Platform: UNKNOWN
Classifier: Programming Language :: Python :: 3.6
Requires-Python: >=3
